PyHa/IsoAutio.py
PyHa/__init__.py
PyHa/annotation_post_processing.py
PyHa/statistics.py
PyHa/visualizations.py
PyHa-test/IsoAutio.py
PyHa-test/__init__.py
PyHa-test/annotation_post_processing.py
PyHa-test/statistics.py
PyHa-test/visualizations.py
PyHa_test/IsoAutio.py
PyHa_test/__init__.py
PyHa_test/annotation_post_processing.py
PyHa_test/statistics.py
PyHa_test/visualizations.py
PyHa_test-0.0.19.dist-info/LICENSE
PyHa_test-0.0.19.dist-info/METADATA
PyHa_test-0.0.19.dist-info/WHEEL
PyHa_test-0.0.19.dist-info/top_level.txt
PyHa_test-0.0.19.dist-info/RECORD
