Metadata-Version: 2.1
Name: PyHa-test
Version: 0.0.19
Summary: A python package for automatically detecting species and comparing to ground truth
Home-page: UNKNOWN
Author: Jacob Ayers, Sean Perry, Sam Prestrelski, Vannessa Salgado
Author-email: UNKNOWN
License: UNKNOWN
Keywords: python
Platform: UNKNOWN
Classifier: Development Status :: 3 - Alpha
Classifier: Programming Language :: Python :: 3.7
Classifier: Operating System :: MacOS :: MacOS X
Classifier: Operating System :: Microsoft :: Windows
Requires-Dist: Keras
Requires-Dist: librosa
Requires-Dist: matplotlib
Requires-Dist: microfaune-ai
Requires-Dist: numpy
Requires-Dist: opensoundscape
Requires-Dist: pandas
Requires-Dist: pydub
Requires-Dist: scikit-image
Requires-Dist: scikit-learn
Requires-Dist: scipy
Requires-Dist: seaborn
Requires-Dist: SoundFile
Requires-Dist: tensorflow
Requires-Dist: torch
Requires-Dist: freetype-py
